ahum_ai/__init__.py
suryaansh-0.0.1.dist-info/METADATA
suryaansh-0.0.1.dist-info/WHEEL
suryaansh-0.0.1.dist-info/top_level.txt
suryaansh-0.0.1.dist-info/RECORD
