Metadata-Version: 2.4
Name: Suryaansh
Version: 0.0.1
Summary: the is my read me
Author: ULTRON
Requires-Python: >=3.6
Dynamic: author
Dynamic: requires-python
Dynamic: summary
